.gitignore
.travis.yml
CHANGES.txt
README.rst
setup.cfg
setup.py
examples/composite-imperative.py
examples/composite.py
examples/countries.txt
examples/simple.jinja2
examples/simple.py
examples/simplefield.jinja2
examples/simplefield.py
pform/__init__.py
pform/button.py
pform/composite.py
pform/directives.py
pform/field.py
pform/fields.py
pform/fieldset.py
pform/form.py
pform/interfaces.py
pform/iso8601.py
pform/validator.py
pform/vocabulary.py
pform.egg-info/PKG-INFO
pform.egg-info/SOURCES.txt
pform.egg-info/dependency_links.txt
pform.egg-info/not-zip-safe
pform.egg-info/requires.txt
pform.egg-info/top_level.txt
pform/templates/bool.jinja2
pform/templates/composite.jinja2
pform/templates/error.jinja2
pform/templates/form-actions.jinja2
pform/templates/form.jinja2
pform/templates/input.jinja2
pform/templates/multichoice.jinja2
pform/templates/options.jinja2
pform/templates/radio.jinja2
pform/templates/select.jinja2
pform/templates/textarea.jinja2
pform/templates/widget-composite.jinja2
pform/templates/widget.jinja2
pform/tests/base.py
pform/tests/test-form.jinja2
pform/tests/test-layout.jinja2
pform/tests/test_button.py
pform/tests/test_composite.py
pform/tests/test_directives.py
pform/tests/test_error.py
pform/tests/test_field.py
pform/tests/test_fields.py
pform/tests/test_fieldset.py
pform/tests/test_form.py
pform/tests/test_iso8601.py
pform/tests/test_timezone.py
pform/tests/test_validator.py
pform/tests/test_vocabulary.py