Metadata-Version: 1.1
Name: pform
Version: 0.6.2
Summary: Form generation library for Pyramid framework
Home-page: https://github.com/fafhrd91/pform/
Author: Nikolay Kim
Author-email: fafhrd91@gmail.com
License: BSD
Platform: UNKNOWN
Classifier: Intended Audience :: Developers
Classifier: Programming Language :: Python
Classifier: Programming Language :: Python :: 2.6
Classifier: Programming Language :: Python :: 2.7
Classifier: Programming Language :: Python :: 3
Classifier: Programming Language :: Python :: 3.2
Classifier: Programming Language :: Python :: 3.3
Classifier: Programming Language :: Python :: Implementation :: CPython
Classifier: Framework :: Pyramid
